pinyiniser/__init__.py
pinyiniser/main.py
pinyiniser/data/cc_cedict_parser.py
pinyiniser/data/cedict_ts_no_space_numerals.u8
pinyiniser/data/cedict_ts_pinyin.u8
pinyiniser/data/jieba_dict_large.txt
pinyiniser/data/pinyin_skip.py
pinyiniser/data/__pycache__/cc_cedict_parser.cpython-39.pyc
pinyiniser/data/__pycache__/pinyin_skip.cpython-39.pyc
Pinyiniser-1.0.3.dist-info/LICENSE.txt
Pinyiniser-1.0.3.dist-info/METADATA
Pinyiniser-1.0.3.dist-info/WHEEL
Pinyiniser-1.0.3.dist-info/top_level.txt
Pinyiniser-1.0.3.dist-info/RECORD
